safe_view/__init__.py
safe_view/main.py
safe_view/quantization.py
safe_view/safe_view.css
safe_view-0.4.0.dist-info/WHEEL
safe_view-0.4.0.dist-info/entry_points.txt
safe_view-0.4.0.dist-info/METADATA
safe_view-0.4.0.dist-info/RECORD
