Metadata-Version: 2.3
Name: safe-view
Version: 0.4.0
Summary: A terminal application to view safetensors files
Author: Elinx
License: MIT
Classifier: Development Status :: 4 - Beta
Classifier: Environment :: Console
Classifier: Intended Audience :: Developers
Classifier: Intended Audience :: Science/Research
Classifier: License :: OSI Approved :: MIT License
Classifier: Operating System :: OS Independent
Classifier: Programming Language :: Python :: 3
Classifier: Programming Language :: Python :: 3.9
Classifier: Programming Language :: Python :: 3.10
Classifier: Programming Language :: Python :: 3.11
Classifier: Programming Language :: Python :: 3.12
Classifier: Topic :: Software Development :: Libraries :: Python Modules
Classifier: Topic :: Utilities
Requires-Dist: textual>=0.40.0
Requires-Dist: safetensors
Requires-Dist: humanize
Requires-Dist: huggingface-hub
Requires-Dist: torch
Requires-Dist: textual-plotext
Requires-Dist: numpy>=2.0.2
Maintainer: Elinx
Requires-Python: >=3.9
Project-URL: Bug Reports, https://github.com/elinx/safe-view/issues
Project-URL: Homepage, https://github.com/elinx/safe-view
Project-URL: Repository, https://github.com/elinx/safe-view
Project-URL: Source Code, https://github.com/elinx/safe-view
